collective.multisearch-2.0.0a3-py3.11-nspkg.pth
collective/multisearch/__init__.py
collective/multisearch/config.py
collective/multisearch/configure.zcml
collective/multisearch/events.py
collective/multisearch/interfaces.py
collective/multisearch/migrations.py
collective/multisearch/profiles.zcml
collective/multisearch/rebuild_i18n.sh
collective/multisearch/utils.py
collective/multisearch/browser/__init__.py
collective/multisearch/browser/configure.zcml
collective/multisearch/browser/interfaces.py
collective/multisearch/browser/manager.py
collective/multisearch/browser/portlet_local_search.py
collective/multisearch/browser/portlet_remote_search.py
collective/multisearch/browser/search.py
collective/multisearch/browser/search_portlet.py
collective/multisearch/browser/search_viewlet.py
collective/multisearch/browser/resources/multisearch.css
collective/multisearch/browser/templates/edit-manager-contextual.pt
collective/multisearch/browser/templates/manage-multisearch.pt
collective/multisearch/browser/templates/multisearch.pt
collective/multisearch/browser/templates/results_portlet.pt
collective/multisearch/browser/templates/search_portlet.pt
collective/multisearch/browser/templates/searchbox_viewlet.pt
collective/multisearch/locales/collective.multisearch.pot
collective/multisearch/locales/plone.pot
collective/multisearch/locales/fr/LC_MESSAGES/collective.multisearch.mo
collective/multisearch/locales/fr/LC_MESSAGES/collective.multisearch.po
collective/multisearch/locales/fr/LC_MESSAGES/plone.mo
collective/multisearch/locales/fr/LC_MESSAGES/plone.po
collective/multisearch/locales/nl/LC_MESSAGES/collective.multisearch.mo
collective/multisearch/locales/nl/LC_MESSAGES/collective.multisearch.po
collective/multisearch/locales/nl/LC_MESSAGES/plone.mo
collective/multisearch/locales/nl/LC_MESSAGES/plone.po
collective/multisearch/profiles/default/browserlayer.xml
collective/multisearch/profiles/default/metadata.xml
collective/multisearch/profiles/default/portlets.xml
collective.multisearch-2.0.0a3.dist-info/METADATA
collective.multisearch-2.0.0a3.dist-info/WHEEL
collective.multisearch-2.0.0a3.dist-info/entry_points.txt
collective.multisearch-2.0.0a3.dist-info/namespace_packages.txt
collective.multisearch-2.0.0a3.dist-info/top_level.txt
collective.multisearch-2.0.0a3.dist-info/RECORD
