Metadata-Version: 2.1
Name: collective.multisearch
Version: 2.0.0a3
Summary: Portlet based display for the Plone search page
Home-page: https://github.com/zestsoftware/collective.multisearch
Author: Zest Software
Author-email: info@zestsoftware.nl
License: GPL
Keywords: multisearch portlet remote
Classifier: Development Status :: 5 - Production/Stable
Classifier: Framework :: Plone
Classifier: Framework :: Plone :: 5.2
Classifier: License :: OSI Approved :: GNU General Public License (GPL)
Classifier: Programming Language :: Python
Classifier: Programming Language :: Python :: 2.7
Classifier: Programming Language :: Python :: 3.6
Classifier: Programming Language :: Python :: 3.7
Classifier: Programming Language :: Python :: 3.8
Classifier: Programming Language :: Python :: 3.9
Requires-Dist: setuptools
Requires-Dist: feedparser
Requires-Dist: plone.api
